is_minified_js/_native__lib.so
is_minified_js/__init__.py
is_minified_js/_native.py
is_minified_js/_native__ffi.py
is_minified_js-0.3.0.dist-info/METADATA
is_minified_js-0.3.0.dist-info/top_level.txt
is_minified_js-0.3.0.dist-info/RECORD
is_minified_js-0.3.0.dist-info/WHEEL
